data/radical_semantic_tag.json
hang/UtilsConcord.py
hang/UtilsGeneral.py
hang/UtilsStats.py
hang/UtilsSubchar.py
hang/UtilsTextProcess.py
hang/__init__.py
hang/compoAnalysis.py
hang/concordSimil.py
hang/concordancer.py
hang/concordancerBase.py
hang/corpus.py
hang/corpusReader.py
hang/database.py
hang/dispersion.py
hang/dispersionStats.py
hang/embeddings.py
hang/fisher_exact.py
hang/senseAnalysis.py
hang/shallowSemanticTag.py
hang/sqlitedict.py
hang/subCharQuery.py
hang/utils.py
hang-0.0.2.dist-info/METADATA
hang-0.0.2.dist-info/WHEEL
hang-0.0.2.dist-info/top_level.txt
hang-0.0.2.dist-info/RECORD
