Metadata-Version: 2.1
Name: hang
Version: 0.0.2
Summary: Hanzi Glyph Corpus Toolkit
Home-page: http://github.com/liao961120/hang
Author: Yongfu Liao
Author-email: liao961120@github.com
License: MIT
Platform: UNKNOWN
Classifier: Programming Language :: Python :: 3
Classifier: License :: OSI Approved :: MIT License
Classifier: Operating System :: OS Independent
Requires-Python: >=3.7
Requires-Dist: scipy
Requires-Dist: gdown (>=3.10.2)
Requires-Dist: pyyaml (>=5.1)
Requires-Dist: cqls
Requires-Dist: tqdm
Requires-Dist: CompoTree
Requires-Dist: hanziPhon
Requires-Dist: pickle5 ; python_version < "3.8.0"
Provides-Extra: all
Requires-Dist: yellowbrick (>=1.3) ; extra == 'all'
Requires-Dist: colorcet ; extra == 'all'
Requires-Dist: datashader ; extra == 'all'
Requires-Dist: scikit-learn ; extra == 'all'
Requires-Dist: scikit-image ; extra == 'all'
Requires-Dist: torch ; extra == 'all'
Requires-Dist: umap-learn ; extra == 'all'
Requires-Dist: bokeh ; extra == 'all'
Requires-Dist: opencc ; extra == 'all'
Requires-Dist: transformers ; extra == 'all'
Requires-Dist: holoviews ; extra == 'all'
Provides-Extra: colab
Requires-Dist: datashader ; extra == 'colab'
Requires-Dist: bokeh ; extra == 'colab'
Requires-Dist: holoviews ; extra == 'colab'
Requires-Dist: scikit-image ; extra == 'colab'
Requires-Dist: colorcet ; extra == 'colab'
Provides-Extra: sense
Requires-Dist: transformers ; extra == 'sense'
Requires-Dist: torch ; extra == 'sense'
Requires-Dist: opencc ; extra == 'sense'
Requires-Dist: umap-learn ; extra == 'sense'
Requires-Dist: yellowbrick (>=1.3) ; extra == 'sense'
Requires-Dist: scikit-learn ; extra == 'sense'
